dmerk/__init__.py
dmerk/cli.py
dmerk/compare.py
dmerk/constants.py
dmerk/merkle.py
dmerk/utils.py
dmerk/generate/__init__.py
dmerk/generate/default.py
dmerk/generate/hashlib_file_digest.py
dmerk/tui/__init__.py
dmerk/tui/styles.tcss
dmerk/tui/widgets/__init__.py
dmerk/tui/widgets/clearable_input.py
dmerk/tui/widgets/compare_widget.py
dmerk/tui/widgets/favorites_sidebar.py
dmerk/tui/widgets/file_manager.py
dmerk/tui/widgets/file_picker.py
dmerk/tui/widgets/sidebar_button.py
dmerk-0.3.0.dist-info/licenses/LICENSE
dmerk-0.3.0.dist-info/METADATA
dmerk-0.3.0.dist-info/WHEEL
dmerk-0.3.0.dist-info/entry_points.txt
dmerk-0.3.0.dist-info/top_level.txt
dmerk-0.3.0.dist-info/RECORD
