Metadata-Version: 2.4
Name: dmerk
Version: 0.3.0
Summary: Generate, Compare and Analyse Directory Merkle Trees
Author-email: Raghuram Krishnaswami <krish.raghuram@gmail.com>
Project-URL: Homepage, https://github.com/krishraghuram/dmerk
Project-URL: Bug Tracker, https://github.com/krishraghuram/dmerk/issues
Classifier: Programming Language :: Python :: 3
Classifier: License :: OSI Approved :: MIT License
Classifier: Operating System :: POSIX :: Linux
Requires-Python: >=3.7
License-File: LICENSE
Requires-Dist: textual
Requires-Dist: humanize
Requires-Dist: platformdirs
Requires-Dist: argcomplete
Provides-Extra: dev
Requires-Dist: textual-dev; extra == "dev"
Requires-Dist: nox; extra == "dev"
Requires-Dist: flake8; extra == "dev"
Requires-Dist: black; extra == "dev"
Requires-Dist: mypy; extra == "dev"
Requires-Dist: coverage; extra == "dev"
Requires-Dist: pytest; extra == "dev"
Requires-Dist: pytest-asyncio; extra == "dev"
Requires-Dist: build; extra == "dev"
Requires-Dist: twine; extra == "dev"
Dynamic: license-file
